hurwitz/__init__.py
hurwitz/hurwitz.py
hurwitz-1.0.0.dist-info/LICENSE
hurwitz-1.0.0.dist-info/METADATA
hurwitz-1.0.0.dist-info/WHEEL
hurwitz-1.0.0.dist-info/top_level.txt
hurwitz-1.0.0.dist-info/RECORD
