Metadata-Version: 2.1
Name: hurwitz
Version: 1.0.0
Summary: A module for working with Hurwitz quaternions
Home-page: https://github.com/HARP-research-Inc/hurwitz
Author: Harper Chisari
Author-email: harper.chisari@harpresearch.ai
Classifier: Programming Language :: Python :: 3
Classifier: License :: OSI Approved :: MIT License
Classifier: Operating System :: OS Independent
Requires-Python: >=3.6
License-File: LICENSE
